{
  "CallerReference": "table-booking-frontend",
  "Comment": "TableBooking Frontend Distribution",
  "DefaultRootObject": "index.html",
  "Origins": {
    "Quantity": 1,
    "Items": [
      {
        "Id": "S3-Origin",
        "DomainName": "table-booking-frontend-ACCOUNT_ID.s3-website-us-east-1.amazonaws.com",
        "CustomOriginConfig": {
          "HTTPPort": 80,
          "HTTPSPort": 443,
          "OriginProtocolPolicy": "http-only"
        }
      }
    ]
  },
  "DefaultCacheBehavior": {
    "TargetOriginId": "S3-Origin",
    "ViewerProtocolPolicy": "redirect-to-https",
    "TrustedSigners": {
      "Enabled": false,
      "Quantity": 0
    },
    "ForwardedValues": {
      "QueryString": false,
      "Cookies": {
        "Forward": "none"
      }
    },
    "MinTTL": 0,
    "DefaultTTL": 86400,
    "MaxTTL": 31536000
  },
  "CacheBehaviors": {
    "Quantity": 0
  },
  "CustomErrorResponses": {
    "Quantity": 1,
    "Items": [
      {
        "ErrorCode": 404,
        "ResponsePagePath": "/index.html",
        "ResponseCode": "200",
        "ErrorCachingMinTTL": 300
      }
    ]
  },
  "PriceClass": "PriceClass_100",
  "Enabled": true
}
